urbans/__init__.py
urbans/translator.py
urbans/utils/__init__.py
urbans/utils/misc.py
urbans/utils/tree_manipulation.py
urbans-0.0.1.dist-info/LICENSE
urbans-0.0.1.dist-info/METADATA
urbans-0.0.1.dist-info/WHEEL
urbans-0.0.1.dist-info/top_level.txt
urbans-0.0.1.dist-info/RECORD
