Metadata-Version: 2.1
Name: urbans
Version: 0.0.1
Summary: URBANS: Universal Rule-based Machine Translation NLP Toolkit
Home-page: https://github.com/urbans/urbans
Author: Truong-Phat Nguyen
Author-email: me@patrickphat.com
License: UNKNOWN
Platform: UNKNOWN
Classifier: Programming Language :: Python :: 3
Classifier: License :: OSI Approved :: MIT License
Classifier: Operating System :: OS Independent
Requires-Python: >3.6
Requires-Dist: nltk (<4)
Provides-Extra: dev
Requires-Dist: pytest ; extra == 'dev'
Requires-Dist: coverage ; extra == 'dev'
